HISTORY.rst
LICENSE
MANIFEST.in
README.rst
rst2beamer.py
setup.py
docs/MANUAL.rst
docs/examples/admonitions.pdf
docs/examples/admonitions.rst
docs/examples/bullets.pdf
docs/examples/bullets.rst
docs/examples/bullets_nooverlay.pdf
docs/examples/codeblocks.pdf
docs/examples/codeblocks.rst
docs/examples/columns.pdf
docs/examples/columns.rst
docs/examples/notes.pdf
docs/examples/notes.rst
docs/examples/notes_shownotes_only.pdf
docs/examples/notes_shownotes_true.pdf
docs/examples/sections.pdf
docs/examples/sections.rst
rst2beamer3k.egg-info/PKG-INFO
rst2beamer3k.egg-info/SOURCES.txt
rst2beamer3k.egg-info/dependency_links.txt
rst2beamer3k.egg-info/entry_points.txt
rst2beamer3k.egg-info/not-zip-safe
rst2beamer3k.egg-info/requires.txt
rst2beamer3k.egg-info/top_level.txt