Metadata-Version: 1.1
Name: rst2beamer3k
Version: 0.9.1
Summary: A docutils writer and script for converting restructured text to the Beamer presentation format
Home-page: https://github.com/myint/rst2beamer
Author: UNKNOWN
Author-email: UNKNOWN
License: GPL
Keywords: presentation docutils rst restructured-text
Platform: UNKNOWN
Classifier: Development Status :: 5 - Production/Stable
Classifier: License :: OSI Approved :: GNU General Public License (GPL)
Classifier: Programming Language :: Python
Classifier: Programming Language :: Python :: 2
Classifier: Programming Language :: Python :: 3
Classifier: Topic :: Text Processing :: Markup
Classifier: Topic :: Utilities
Classifier: Topic :: Multimedia :: Graphics :: Presentation
